Workbook

Sheet Budget Tracker
A1: Date | B1: Item | C1: Amount | D1: Priority | E1: Days Until Due | F1: Status | G1: Paid? | H1: Notes | I1: Due This Week | J1: Due This Month | K1: Remaining Days
A2: 45922 | B2: Affirm | C2: 96.19 | D2: High | E2: 0 | F2: Upcoming | G2: no | I2: =IF(AND(A2>=TODAY(), A2<=TODAY()+7), "Yes", "") | J2: =IF(AND(MONTH(A2)=MONTH(TODAY()), YEAR(A2)=YEAR(TODAY())), "Yes", "") | K2: =A2-TODAY()
A3: 45925 | B3: Affirm | C3: 181.75 | D3: High | E3: 3 | F3: Upcoming | G3: no | I3: =IF(AND(A3>=TODAY(), A3<=TODAY()+7), "Yes", "") | J3: =IF(AND(MONTH(A3)=MONTH(TODAY()), YEAR(A3)=YEAR(TODAY())), "Yes", "") | K3: =A3-TODAY()
A4: 2025-09-26 | B4: Car Payment | C4: 547.9 | D4: High | E4: 4 | F4: Upcoming | G4: yes | I4: =IF(AND(A4>=TODAY(), A4<=TODAY()+7), "Yes", "") | J4: =IF(AND(MONTH(A4)=MONTH(TODAY()), YEAR(A4)=YEAR(TODAY())), "Yes", "") | K4: =A4-TODAY()
A5: 2025-09-26 | B5: Rent Plan (Back) | C5: 142 | D5: High | E5: 4 | F5: Upcoming | G5: yes | I5: =IF(AND(A5>=TODAY(), A5<=TODAY()+7), "Yes", "") | J5: =IF(AND(MONTH(A5)=MONTH(TODAY()), YEAR(A5)=YEAR(TODAY())), "Yes", "") | K5: =A5-TODAY()
A6: 45903 | B6: Flight Ticket | C6: 1200 | D6: High | E6: 8 | F6: Upcoming | G6: no | I6: yes | J6: =IF(AND(MONTH(A6)=MONTH(TODAY()), YEAR(A6)=YEAR(TODAY())), "Yes", "") | K6: =A6-TODAY()
A7: 45930 | B7: Affirm | C7: 86.09 | D7: High | E7: 8 | F7: Upcoming | G7: no | I7: =IF(AND(A7>=TODAY(), A7<=TODAY()+7), "Yes", "") | J7: =IF(AND(MONTH(A7)=MONTH(TODAY()), YEAR(A7)=YEAR(TODAY())), "Yes", "") | K7: =A7-TODAY()
A8: 2025-10-01 | B8: October Rent | C8: 2052.09 | D8: Critical | E8: 9 | F8: Upcoming | G8: yes | H8: 609 | I8: =IF(AND(A8>=TODAY(), A8<=TODAY()+7), "Yes", "") | J8: =IF(AND(MONTH(A8)=MONTH(TODAY()), YEAR(A8)=YEAR(TODAY())), "Yes", "") | K8: =A8-TODAY()
A9: 2025-10-10 | B9: Capital One | C9: 200 | D9: High | E9: 18 | F9: Upcoming | G9: yes | I9: =IF(AND(A9>=TODAY(), A9<=TODAY()+7), "Yes", "") | J9: =IF(AND(MONTH(A9)=MONTH(TODAY()), YEAR(A9)=YEAR(TODAY())), "Yes", "") | K9: =A9-TODAY()
A10: 45940 | B10: FPL | C10: 50.12 | D10: High | E10: 16 | F10: Upcoming | G10: yes | H10: =403.91-C10 | I10: =IF(AND(A10>=TODAY(), A10<=TODAY()+7), "Yes", "") | J10: =IF(AND(MONTH(A10)=MONTH(TODAY()), YEAR(A10)=YEAR(TODAY())), "Yes", "") | K10: =A10-TODAY()
A11: 45935 | B11: Mazda | C11: 308 | D11: High | E11: 28 | F11: Upcoming | G11: yes | H11: scheduled | I11: =IF(AND(A11>=TODAY(), A11<=TODAY()+7), "Yes", "") | J11: =IF(AND(MONTH(A11)=MONTH(TODAY()), YEAR(A11)=YEAR(TODAY())), "Yes", "") | K11: =A11-TODAY()
A12: 45930 | B12: Mariner | C12: 359 | D12: High | E12: 28 | F12: Upcoming | G12: yes | I12: =IF(AND(A12>=TODAY(), A12<=TODAY()+7), "Yes", "") | J12: =IF(AND(MONTH(A12)=MONTH(TODAY()), YEAR(A12)=YEAR(TODAY())), "Yes", "") | K12: =A12-TODAY()
A13: 45935 | B13: JVT | C13: 312 | D13: High | E13: 0 | F13: Upcoming | G13: yes | I13: =IF(AND(A13>=TODAY(), A13<=TODAY()+7), "Yes", "") | J13: =IF(AND(MONTH(A13)=MONTH(TODAY()), YEAR(A13)=YEAR(TODAY())), "Yes", "") | K13: =A13-TODAY()
A14: 45926 | B14: Miscellaneous | C14: 89 | D14: Low | E14: 0 | F14: Upcoming | G14: no | H14: done | I14: =IF(AND(A14>=TODAY(), A14<=TODAY()+7), "Yes", "") | J14: =IF(AND(MONTH(A14)=MONTH(TODAY()), YEAR(A14)=YEAR(TODAY())), "Yes", "") | K14: =A14-TODAY()
A15: 45930 | B15: Progressive | C15: 179.66 | D15: Medium | E15: 4 | F15: Upcoming | G15: yes | I15: =IF(AND(A15>=TODAY(), A15<=TODAY()+7), "Yes", "") | J15: =IF(AND(MONTH(A15)=MONTH(TODAY()), YEAR(A15)=YEAR(TODAY())), "Yes", "") | K15: =A15-TODAY()
A16: 45930 | B16: Alliance | C16: 151 | D16: Medium | E16: 4 | F16: Upcoming | G16: yes | I16: =IF(AND(A16>=TODAY(), A16<=TODAY()+7), "Yes", "") | J16: =IF(AND(MONTH(A16)=MONTH(TODAY()), YEAR(A16)=YEAR(TODAY())), "Yes", "") | K16: =A16-TODAY()
A17: 45930 | B17: Sloan | C17: 150.75 | D17: High | E17: 35 | F17: Upcoming | G17: yes | H17: scheduled | I17: =IF(AND(A17>=TODAY(), A17<=TODAY()+7), "Yes", "") | J17: =IF(AND(MONTH(A17)=MONTH(TODAY()), YEAR(A17)=YEAR(TODAY())), "Yes", "") | K17: =A17-TODAY()
A18: 45926 | B18: Fortina | C18: 40 | D18: Low | E18: 0 | F18: Due now | G18: yes | I18: =IF(AND(A18>=TODAY(), A18<=TODAY()+7), "Yes", "") | J18: =IF(AND(MONTH(A18)=MONTH(TODAY()), YEAR(A18)=YEAR(TODAY())), "Yes", "") | K18: =A18-TODAY()
A19: 45940 | B19: Mariner | C19: 359 | D19: High | E19: 30 | F19: upcoming | G19: yes | H19: scheduled | I19: =IF(AND(A19>=TODAY(), A19<=TODAY()+7), "Yes", "") | J19: =IF(AND(MONTH(A19)=MONTH(TODAY()), YEAR(A19)=YEAR(TODAY())), "Yes", "") | K19: =A19-TODAY()
A20: 101-0-2025 | B20: Adjustment | C20: 652 | G20: yes | I20: =IF(AND(A20>=TODAY(), A20<=TODAY()+7), "Yes", "") | J20: =IF(AND(MONTH(A20)=MONTH(TODAY()), YEAR(A20)=YEAR(TODAY())), "Yes", "") | K20: =A20-TODAY()
A21: Progressive | C21: 179 | G21: yes | I21: =IF(AND(A21>=TODAY(), A21<=TODAY()+7), "Yes", "") | J21: =IF(AND(MONTH(A21)=MONTH(TODAY()), YEAR(A21)=YEAR(TODAY())), "Yes", "") | K21: =A21-TODAY()
A22: Alliance | C22: =155+25 | G22: yes | I22: =IF(AND(A22>=TODAY(), A22<=TODAY()+7), "Yes", "") | J22: =IF(AND(MONTH(A22)=MONTH(TODAY()), YEAR(A22)=YEAR(TODAY())), "Yes", "") | K22: =A22-TODAY()
A23: 45955 | B23: car | C23: 547.9 | D23: Low | E23: 12 | F23: Upcoming | G23: no | I23: no | J23: =IF(AND(MONTH(A23)=MONTH(TODAY()), YEAR(A23)=YEAR(TODAY())), "Yes", "") | K23: =A23-TODAY()
A24: 45954 | B24: Rent | C24: 603 | D24: Low | E24: 0 | F24: Upcoming | G24: no | I24: =IF(AND(A24>=TODAY(), A24<=TODAY()+7), "Yes", "") | J24: =IF(AND(MONTH(A24)=MONTH(TODAY()), YEAR(A24)=YEAR(TODAY())), "Yes", "") | K24: =A24-TODAY()
A25: 45947 | B25: Newera | C25: 303 | D25: Low | E25: 0 | F25: Upcoming | G25: no | I25: =IF(AND(A25>=TODAY(), A25<=TODAY()+7), "Yes", "") | J25: =IF(AND(MONTH(A25)=MONTH(TODAY()), YEAR(A25)=YEAR(TODAY())), "Yes", "") | K25: =A25-TODAY()
H26: =IF(AND(MONTH(A26)=MONTH(TODAY()), YEAR(A26)=YEAR(TODAY())), "Yes", "") | I26: =IF(AND(A26>=TODAY(), A26<=TODAY()+7), "Yes", "") | J26: =IF(AND(MONTH(A26)=MONTH(TODAY()), YEAR(A26)=YEAR(TODAY())), "Yes", "") | K26: =A26-TODAY()
H27: =IF(AND(MONTH(A27)=MONTH(TODAY()), YEAR(A27)=YEAR(TODAY())), "Yes", "") | I27: =IF(AND(A27>=TODAY(), A27<=TODAY()+7), "Yes", "") | J27: =IF(AND(MONTH(A27)=MONTH(TODAY()), YEAR(A27)=YEAR(TODAY())), "Yes", "") | K27: =A27-TODAY()
H28: =IF(AND(MONTH(A28)=MONTH(TODAY()), YEAR(A28)=YEAR(TODAY())), "Yes", "") | I28: =IF(AND(A28>=TODAY(), A28<=TODAY()+7), "Yes", "") | J28: =IF(AND(MONTH(A28)=MONTH(TODAY()), YEAR(A28)=YEAR(TODAY())), "Yes", "") | K28: =A28-TODAY()
H29: =IF(AND(MONTH(A29)=MONTH(TODAY()), YEAR(A29)=YEAR(TODAY())), "Yes", "") | I29: =IF(AND(A29>=TODAY(), A29<=TODAY()+7), "Yes", "") | J29: =IF(AND(MONTH(A29)=MONTH(TODAY()), YEAR(A29)=YEAR(TODAY())), "Yes", "") | K29: =A29-TODAY()
H30: =IF(AND(MONTH(A30)=MONTH(TODAY()), YEAR(A30)=YEAR(TODAY())), "Yes", "") | I30: =IF(AND(A30>=TODAY(), A30<=TODAY()+7), "Yes", "") | J30: =IF(AND(MONTH(A30)=MONTH(TODAY()), YEAR(A30)=YEAR(TODAY())), "Yes", "") | K30: =A30-TODAY()
H31: =IF(AND(MONTH(A31)=MONTH(TODAY()), YEAR(A31)=YEAR(TODAY())), "Yes", "") | I31: =IF(AND(A31>=TODAY(), A31<=TODAY()+7), "Yes", "") | J31: =IF(AND(MONTH(A31)=MONTH(TODAY()), YEAR(A31)=YEAR(TODAY())), "Yes", "") | K31: =A31-TODAY()
H32: =IF(AND(MONTH(A32)=MONTH(TODAY()), YEAR(A32)=YEAR(TODAY())), "Yes", "") | I32: =IF(AND(A32>=TODAY(), A32<=TODAY()+7), "Yes", "") | J32: =IF(AND(MONTH(A32)=MONTH(TODAY()), YEAR(A32)=YEAR(TODAY())), "Yes", "") | K32: =A32-TODAY()
H33: =IF(AND(MONTH(A33)=MONTH(TODAY()), YEAR(A33)=YEAR(TODAY())), "Yes", "") | I33: =IF(AND(A33>=TODAY(), A33<=TODAY()+7), "Yes", "") | J33: =IF(AND(MONTH(A33)=MONTH(TODAY()), YEAR(A33)=YEAR(TODAY())), "Yes", "") | K33: =A33-TODAY()
H34: =IF(AND(MONTH(A34)=MONTH(TODAY()), YEAR(A34)=YEAR(TODAY())), "Yes", "") | I34: =IF(AND(A34>=TODAY(), A34<=TODAY()+7), "Yes", "") | J34: =IF(AND(MONTH(A34)=MONTH(TODAY()), YEAR(A34)=YEAR(TODAY())), "Yes", "") | K34: =A34-TODAY()
H35: =IF(AND(MONTH(A35)=MONTH(TODAY()), YEAR(A35)=YEAR(TODAY())), "Yes", "") | I35: =IF(AND(A35>=TODAY(), A35<=TODAY()+7), "Yes", "") | J35: =IF(AND(MONTH(A35)=MONTH(TODAY()), YEAR(A35)=YEAR(TODAY())), "Yes", "") | K35: =A35-TODAY()
H36: =IF(AND(MONTH(A36)=MONTH(TODAY()), YEAR(A36)=YEAR(TODAY())), "Yes", "") | I36: =IF(AND(A36>=TODAY(), A36<=TODAY()+7), "Yes", "") | J36: =IF(AND(MONTH(A36)=MONTH(TODAY()), YEAR(A36)=YEAR(TODAY())), "Yes", "") | K36: =A36-TODAY()
H37: =IF(AND(MONTH(A37)=MONTH(TODAY()), YEAR(A37)=YEAR(TODAY())), "Yes", "") | I37: =IF(AND(A37>=TODAY(), A37<=TODAY()+7), "Yes", "") | J37: =IF(AND(MONTH(A37)=MONTH(TODAY()), YEAR(A37)=YEAR(TODAY())), "Yes", "") | K37: =A37-TODAY()
... H39: =IF(AND(MONTH(A39)=MONTH(TODAY()), YEAR(A39)=YEAR(TODAY())), "Yes", "") | I39: =IF(AND(A39>=TODAY(), A39<=TODAY()+7), "Yes", "") | J39: =IF(AND(MONTH(A39)=MONTH(TODAY()), YEAR(A39)=YEAR(TODAY())), "Yes", "") | K39: =A39-TODAY()

Sheet Income
A1: Date | B1: Source | C1: Amount
A2: 2025-09-22 | B2: Reserve | C2: 700
A3: 2025-09-26 | B3: Paycheck | C3: 3800
A4: 2025-10-10 | B4: Paycheck | C4: 3800
A5: 45954 | B5: Paycheck | C5: 0

Sheet Dashboard
A1: Budget Dashboard
A2: Total Income | B2: =SUM(Income!C2:C100)
A3: Total Due This Week | B3: =SUMIFS('Budget Tracker'!C:C, 'Budget Tracker'!I:I, "Yes")
A4: Total Due This Month | B4: =SUMIFS('Budget Tracker'!C:C, 'Budget Tracker'!J:J, "Yes")
A5: Total Overdue | B5: =SUMIFS('Budget Tracker'!C:C, 'Budget Tracker'!K:K, "<0", 'Budget Tracker'!F:F, "Upcoming")
A6: Total Paid | B6: =SUMIFS('Budget Tracker'!C:C, 'Budget Tracker'!G:G, "yes")
